poetry_workspace_plugin/__init__.py
poetry_workspace_plugin/console/__init__.py
poetry_workspace_plugin/console/commands/__init__.py
poetry_workspace_plugin/console/commands/add.py
poetry_workspace_plugin/console/commands/dependees.py
poetry_workspace_plugin/console/commands/list.py
poetry_workspace_plugin/console/commands/new.py
poetry_workspace_plugin/console/commands/remove.py
poetry_workspace_plugin/console/commands/run.py
poetry_workspace_plugin/helpers.py
poetry_workspace_plugin/plugin.py
poetry_workspace_plugin/py.typed
poetry_workspaces-0.1.0.dist-info/entry_points.txt
poetry_workspaces-0.1.0.dist-info/LICENSE.txt
poetry_workspaces-0.1.0.dist-info/WHEEL
poetry_workspaces-0.1.0.dist-info/METADATA
poetry_workspaces-0.1.0.dist-info/RECORD
