Metadata-Version: 2.1
Name: poetry-workspaces
Version: 0.1.0
Summary: Poetry workspace plugin for Python monorepos.
Home-page: https://github.com/jacksmith15/poetry-workspace-plugin
Author: Jack Smith
Requires-Python: >=3.9,<4.0
Classifier: Programming Language :: Python :: 3
Classifier: Programming Language :: Python :: 3.9
Classifier: Programming Language :: Python :: 3.10
Requires-Dist: poetry (>=1.2.0a1,<2.0.0)
Project-URL: Repository, https://github.com/jacksmith15/poetry-workspace-plugin
